exafs-1.2.1.dist-info/licenses/LICENSE
flowapp/__about__.py
flowapp/__init__.py
flowapp/auth.py
flowapp/constants.py
flowapp/flowspec.py
flowapp/instance_config.py
flowapp/messages.py
flowapp/output.py
flowapp/validators.py
flowapp/forms/__init__.py
flowapp/forms/api.py
flowapp/forms/base.py
flowapp/forms/choices.py
flowapp/forms/organization.py
flowapp/forms/user.py
flowapp/forms/rules/__init__.py
flowapp/forms/rules/base.py
flowapp/forms/rules/ipv4.py
flowapp/forms/rules/ipv6.py
flowapp/forms/rules/rtbh.py
flowapp/forms/rules/whitelist.py
flowapp/models/__init__.py
flowapp/models/api.py
flowapp/models/base.py
flowapp/models/community.py
flowapp/models/log.py
flowapp/models/organization.py
flowapp/models/user.py
flowapp/models/utils.py
flowapp/models/rules/__init__.py
flowapp/models/rules/base.py
flowapp/models/rules/flowspec.py
flowapp/models/rules/rtbh.py
flowapp/models/rules/whitelist.py
flowapp/services/__init__.py
flowapp/services/base.py
flowapp/services/rule_service.py
flowapp/services/whitelist_common.py
flowapp/services/whitelist_service.py
flowapp/static/mystyle.css
flowapp/static/swagger.yml
flowapp/static/js/check_all.js
flowapp/static/js/enable_tooltips.js
flowapp/static/js/ip_context.js
flowapp/static/js/search_helpers.js
flowapp/templates/macros.html
flowapp/templates/pagination_macro.html
flowapp/templates/errors/401.html
flowapp/templates/errors/401.j2
flowapp/templates/errors/404.html
flowapp/templates/errors/500.html
flowapp/templates/forms/api_key.html
flowapp/templates/forms/bulk_user_form.html
flowapp/templates/forms/ipv4_rule.html
flowapp/templates/forms/ipv6_rule.html
flowapp/templates/forms/machine_api_key.html
flowapp/templates/forms/macros.html
flowapp/templates/forms/org.html
flowapp/templates/forms/rtbh_rule.html
flowapp/templates/forms/rule.html
flowapp/templates/forms/simple_form.html
flowapp/templates/forms/whitelist.html
flowapp/templates/layouts/default.html
flowapp/templates/pages/actions.html
flowapp/templates/pages/api_key.html
flowapp/templates/pages/as_paths.html
exafs-1.2.1.dist-info/METADATA
exafs-1.2.1.dist-info/WHEEL
exafs-1.2.1.dist-info/top_level.txt
exafs-1.2.1.dist-info/RECORD
