Metadata-Version: 2.4
Name: exafs
Version: 1.2.1
Summary: Tool for creation, validation, and execution of ExaBGP messages for network security.
Author: Jiri Vrany, Petr Adamec, Josef Verich, Jakub Man
Maintainer-email: Jiri Vrany <jiri.vrany@cesnet.cz>
License-Expression: MIT
Project-URL: Homepage, https://github.com/CESNET/exafs
Project-URL: Repository, https://github.com/CESNET/exafs
Project-URL: Documentation, https://github.com/CESNET/exafs/blob/master/README.md
Project-URL: Issues, https://github.com/CESNET/exafs/issues
Project-URL: Changelog, https://github.com/CESNET/exafs/blob/master/README.md
Keywords: bgp,exabgp,flowspec,ddos,network-security,CESNET
Classifier: Development Status :: 4 - Beta
Classifier: Intended Audience :: System Administrators
Classifier: Intended Audience :: Telecommunications Industry
Classifier: Operating System :: OS Independent
Classifier: Programming Language :: Python :: 3
Classifier: Programming Language :: Python :: 3.9
Classifier: Programming Language :: Python :: 3.10
Classifier: Programming Language :: Python :: 3.11
Classifier: Programming Language :: Python :: 3.12
Classifier: Programming Language :: Python :: 3.13
Classifier: Topic :: System :: Networking
Classifier: Topic :: Security
Classifier: Framework :: Flask
Requires-Python: >=3.9
License-File: LICENSE
Requires-Dist: Flask>=2.0.2
Requires-Dist: Flask-SQLAlchemy>=2.2
Requires-Dist: Flask-SSO>=0.4.0
Requires-Dist: Flask-WTF>=1.0.0
Requires-Dist: Flask-Migrate>=3.0.0
Requires-Dist: Flask-Script>=2.0.0
Requires-Dist: Flask-Session
Requires-Dist: PyJWT>=2.4.0
Requires-Dist: PyMySQL>=1.0.0
Requires-Dist: requests>=2.20.0
Requires-Dist: babel>=2.7.0
Requires-Dist: email_validator>=1.1
Requires-Dist: pika>=1.3.0
Requires-Dist: loguru
Requires-Dist: flasgger
Requires-Dist: python-dotenv
Provides-Extra: dev
Requires-Dist: pytest>=7.0.0; extra == "dev"
Dynamic: license-file
